README.md
setup.py
linux_thermaltake_rgb/__init__.py
linux_thermaltake_rgb/classified_object.py
linux_thermaltake_rgb/controllers.py
linux_thermaltake_rgb/drivers.py
linux_thermaltake_rgb/fan_manager.py
linux_thermaltake_rgb/globals.py
linux_thermaltake_rgb/lighting_manager.py
linux_thermaltake_rgb.egg-info/PKG-INFO
linux_thermaltake_rgb.egg-info/SOURCES.txt
linux_thermaltake_rgb.egg-info/dependency_links.txt
linux_thermaltake_rgb.egg-info/entry_points.txt
linux_thermaltake_rgb.egg-info/requires.txt
linux_thermaltake_rgb.egg-info/top_level.txt
linux_thermaltake_rgb/assets/config.yml
linux_thermaltake_rgb/assets/linux-thermaltake-rgb.service
linux_thermaltake_rgb/daemon/__init__.py
linux_thermaltake_rgb/daemon/config.py
linux_thermaltake_rgb/daemon/daemon.py
linux_thermaltake_rgb/daemon/main.py
linux_thermaltake_rgb/devices/__init__.py
linux_thermaltake_rgb/devices/fans.py
linux_thermaltake_rgb/devices/lights.py
linux_thermaltake_rgb/devices/pumps.py
tests/__init__.py
tests/run_tests.py