Metadata-Version: 1.2
Name: linux-thermaltake-rgb
Version: 0.2.0.post1555598565
Summary: python driver and daemon for thermaltake hardware products
Home-page: https://github.com/chestm007/linux_thermaltake_rgb
Author: Max Chesterfield
Author-email: chestm007@hotmail.com
Maintainer: Max Chesterfield
Maintainer-email: chestm007@hotmail.com
License: GPL-2.0
Platform: UNKNOWN
